CHANGELOG.rst
CONTRIBUTING.md
MANIFEST.in
Makefile
README.md
RELEASE.md
requirements-dev.txt
requirements-tests.txt
requirements.txt
setup.cfg
setup.py
crossdock/server/__init__.py
crossdock/server/constants.py
crossdock/server/endtoend.py
crossdock/server/serializer.py
crossdock/server/server.py
crossdock/server/thriftrw_serializer.py
crossdock/thrift_gen/__init__.py
crossdock/thrift_gen/tracetest/TracedService.py
crossdock/thrift_gen/tracetest/__init__.py
crossdock/thrift_gen/tracetest/constants.py
crossdock/thrift_gen/tracetest/ttypes.py
jaeger_client/TUDPTransport.py
jaeger_client/__init__.py
jaeger_client/codecs.py
jaeger_client/config.py
jaeger_client/constants.py
jaeger_client/ioloop_util.py
jaeger_client/local_agent_net.py
jaeger_client/rate_limiter.py
jaeger_client/reporter.py
jaeger_client/sampler.py
jaeger_client/senders.py
jaeger_client/span.py
jaeger_client/span_context.py
jaeger_client/thrift.py
jaeger_client/throttler.py
jaeger_client/tracer.py
jaeger_client/utils.py
jaeger_client/metrics/__init__.py
jaeger_client/metrics/metrics.py
jaeger_client/metrics/prometheus.py
jaeger_client/thrift_gen/__init__.py
jaeger_client/thrift_gen/agent/Agent.py
jaeger_client/thrift_gen/agent/__init__.py
jaeger_client/thrift_gen/agent/constants.py
jaeger_client/thrift_gen/agent/ttypes.py
jaeger_client/thrift_gen/jaeger/Collector.py
jaeger_client/thrift_gen/jaeger/__init__.py
jaeger_client/thrift_gen/jaeger/constants.py
jaeger_client/thrift_gen/jaeger/ttypes.py
jaeger_client/thrift_gen/sampling/SamplingManager.py
jaeger_client/thrift_gen/sampling/__init__.py
jaeger_client/thrift_gen/sampling/constants.py
jaeger_client/thrift_gen/sampling/ttypes.py
jaeger_client/thrift_gen/zipkincore/ZipkinCollector.py
jaeger_client/thrift_gen/zipkincore/__init__.py
jaeger_client/thrift_gen/zipkincore/constants.py
jaeger_client/thrift_gen/zipkincore/ttypes.py
sfx_jaeger_client.egg-info/PKG-INFO
sfx_jaeger_client.egg-info/SOURCES.txt
sfx_jaeger_client.egg-info/dependency_links.txt
sfx_jaeger_client.egg-info/not-zip-safe
sfx_jaeger_client.egg-info/requires.txt
sfx_jaeger_client.egg-info/top_level.txt
tests/__init__.py
tests/conftest.py
tests/test_TUDPTransport.py
tests/test_api.py
tests/test_codecs.py
tests/test_config.py
